starlette_context/__init__.py
starlette_context/ctx.py
starlette_context/errors.py
starlette_context/header_keys.py
starlette_context/py.typed
starlette_context/middleware/__init__.py
starlette_context/middleware/context_middleware.py
starlette_context/middleware/raw_middleware.py
starlette_context/plugins/__init__.py
starlette_context/plugins/api_key.py
starlette_context/plugins/base.py
starlette_context/plugins/correlation_id.py
starlette_context/plugins/date_header.py
starlette_context/plugins/forwarded_for.py
starlette_context/plugins/request_id.py
starlette_context/plugins/user_agent.py
starlette_context-0.3.5.dist-info/LICENSE
starlette_context-0.3.5.dist-info/METADATA
starlette_context-0.3.5.dist-info/WHEEL
starlette_context-0.3.5.dist-info/top_level.txt
starlette_context-0.3.5.dist-info/RECORD
