Metadata-Version: 2.1
Name: starlette-context
Version: 0.3.5
Summary: Access context in Starlette
Home-page: https://github.com/tomwojcik/starlette-context
Download-URL: https://github.com/tomwojcik/starlette-context/archive/0.3.5.tar.gz
Author: Tomasz Wojcik
License: MIT
Keywords: starlette,fastapi
Platform: any
Classifier: Development Status :: 4 - Beta
Classifier: Intended Audience :: Developers
Classifier: Topic :: Software Development :: Build Tools
Classifier: License :: OSI Approved :: MIT License
Classifier: Programming Language :: Python :: 3.7
Classifier: Programming Language :: Python :: 3.8
Classifier: Programming Language :: Python :: 3.9
Requires-Python: >=3.7
License-File: LICENSE
